jupyterlab_optuna/__init__.py
jupyterlab_optuna/_version.py
jupyterlab_optuna/handlers.py
jupyterlab_optuna/vendor/optuna_dashboard/.gitignore
jupyterlab_optuna/vendor/optuna_dashboard/__init__.py
jupyterlab_optuna/vendor/optuna_dashboard/_app.py
jupyterlab_optuna/vendor/optuna_dashboard/_bottle_util.py
jupyterlab_optuna/vendor/optuna_dashboard/_cli.py
jupyterlab_optuna/vendor/optuna_dashboard/_config.py
jupyterlab_optuna/vendor/optuna_dashboard/_custom_plot_data.py
jupyterlab_optuna/vendor/optuna_dashboard/_form_widget.py
jupyterlab_optuna/vendor/optuna_dashboard/_importance.py
jupyterlab_optuna/vendor/optuna_dashboard/_inmemory_cache.py
jupyterlab_optuna/vendor/optuna_dashboard/_named_objectives.py
jupyterlab_optuna/vendor/optuna_dashboard/_note.py
jupyterlab_optuna/vendor/optuna_dashboard/_pareto_front.py
jupyterlab_optuna/vendor/optuna_dashboard/_preference_setting.py
jupyterlab_optuna/vendor/optuna_dashboard/_preferential_history.py
jupyterlab_optuna/vendor/optuna_dashboard/_rdb_migration.py
jupyterlab_optuna/vendor/optuna_dashboard/_serializer.py
jupyterlab_optuna/vendor/optuna_dashboard/_sql_profiler.py
jupyterlab_optuna/vendor/optuna_dashboard/_storage.py
jupyterlab_optuna/vendor/optuna_dashboard/_storage_url.py
jupyterlab_optuna/vendor/optuna_dashboard/app.py
jupyterlab_optuna/vendor/optuna_dashboard/index.html
jupyterlab_optuna/vendor/optuna_dashboard/package-lock.json
jupyterlab_optuna/vendor/optuna_dashboard/package.json
jupyterlab_optuna/vendor/optuna_dashboard/tsconfig.json
jupyterlab_optuna/vendor/optuna_dashboard/tsconfig.pkg.json
jupyterlab_optuna/vendor/optuna_dashboard/webpack.config.js
jupyterlab_optuna/vendor/optuna_dashboard/artifact/__init__.py
jupyterlab_optuna/vendor/optuna_dashboard/artifact/_backend.py
jupyterlab_optuna/vendor/optuna_dashboard/artifact/_backend_to_store.py
jupyterlab_optuna/vendor/optuna_dashboard/artifact/backoff.py
jupyterlab_optuna/vendor/optuna_dashboard/artifact/boto3.py
jupyterlab_optuna-0.2.4.dist-info/METADATA
jupyterlab_optuna-0.2.4.dist-info/WHEEL
jupyterlab_optuna-0.2.4.dist-info/RECORD
